{"py/object": "rasa.core.featurizers.tracker_featurizers.IntentMaxHistoryTrackerFeaturizer", "state_featurizer": {"py/object": "rasa.core.featurizers.single_state_featurizer.IntentTokenizerSingleStateFeaturizer", "_default_feature_states": {"intent": {"airforce_career": 0, "airforce_qualifications": 1, "army_career": 2, "army_navy_airforce_career_paths": 3, "army_qualifications": 4, "back": 5, "english_marks": 6, "get_career_guidance": 7, "get_user_grade": 8, "greet": 9, "maths_marks": 10, "navy_career": 11, "navy_qualifications": 12, "negative_feedback": 13, "nlu_fallback": 14, "no_button_selection": 15, "out_of_scope": 16, "pcb_career_paths": 17, "pcm_career_paths": 18, "pcmb_career_paths": 19, "positive_feedback": 20, "restart": 21, "science_marks": 22, "science_subject_combination": 23, "session_start": 24, "social_studies_marks": 25}, "action_name": {"action_listen": 0, "action_restart": 1, "action_session_start": 2, "action_default_fallback": 3, "action_deactivate_loop": 4, "action_revert_fallback_events": 5, "action_default_ask_affirmation": 6, "action_default_ask_rephrase": 7, "action_two_stage_fallback": 8, "action_unlikely_intent": 9, "action_back": 10, "...": 11, "action_extract_slots": 12, "utter_positive_feedback": 13, "utter_pcb_career_paths": 14, "utter_science_subject_combination": 15, "action_validate_form_maths": 16, "utter_science_marks": 17, "utter_greet": 18, "utter_get_career_guidance": 19, "utter_social_studies_marks": 20, "utter_maths_marks": 21, "action_get_user_grade": 22, "utter_negative_feedback": 23, "utter_pcmb_career_paths": 24, "utter_pcm_career_paths": 25, "action_validate_form_sci": 26, "action_validate_form_eng": 27, "action_validate_form_ss": 28, "action_career_prediction": 29, "utter_army_navy_airforce_career_paths": 30, "utter_army_career": 31, "utter_army_qualifications": 32, "utter_navy_career": 33, "utter_navy_qualifications": 34, "utter_airforce_career": 35, "utter_airforce_qualifications": 36, "utter_no_button_selection": 37, "utter_please_rephrase": 38}, "entities": {"g_level": 0, "m_eng": 1, "m_maths": 2, "m_sci": 3, "m_ss": 4}, "slots": {}, "active_loop": {}}, "action_texts": [], "entity_tag_specs": []}, "max_history": 5, "remove_duplicates": true}